{
  "nfts": [
    {
      "image": "https://asda.scene7.com/is/image/Asda/5063089286623?hei=748&wid=556&qlt=85&fmt=pjpg&resmode=sharp2&op_usm=1.1,0.5,0,0&defaultimage=default_details_George_rd",
      "title": "Pudgy Bears",
      "rank": "Pudgy Bears #189",
      "author": "Author 1",
      "price_eth": 2.5,
      "price_usd": 6000,
      "id": "7aeb"
    },
    {
      "image": "https://encrypted-tbn0.gstatic.com/images?q=tbn:ANd9GcSjOtZsZsuzrmwQ56Jhkj11Hm-tvx8Tzw5ASw&s",
      "title": "Crypto Kitties",
      "rank": "Crypto Kitties #42",
      "author": "Author 2",
      "price_eth": 1.8,
      "price_usd": 4320,
      "id": "f75f"
    },
    {
      "image": "https://encrypted-tbn0.gstatic.com/images?q=tbn:ANd9GcThg-iDdR8oVSRpnnLvv2NMzTEdw2e0f9i-Ug&s",
      "title": "Bored Apes",
      "rank": "Bored Apes #150",
      "author": "Author 3",
      "price_eth": 3.1,
      "price_usd": 7440,
      "id": "6db9"
    },
    {
      "image": "https://encrypted-tbn0.gstatic.com/images?q=tbn:ANd9GcRdB8JJtVnVU1vw8reNAKCKuxArNZFx7YC1Xw&s",
      "title": "Meebits",
      "rank": "Meebits #77",
      "author": "Author 4",
      "price_eth": 2,
      "price_usd": 4800,
      "id": "b86b"
    },
    {
      "image": "https://encrypted-tbn0.gstatic.com/images?q=tbn:ANd9GcQluXEJyqYthGDWHTh5vUh3ht7ih6za78uJYw&s",
      "title": "Art Blocks",
      "rank": "Art Blocks #233",
      "author": "Author 5",
      "price_eth": 1.2,
      "price_usd": 2880,
      "id": "b65a"
    },
    {
      "id": "83d4",
      "image": "https://encrypted-tbn0.gstatic.com/images?q=tbn:ANd9GcS_SuHzyB2Wd2lkzV_oKwXC2L72Gkt4_EuzgA&s",
      "title": "Barbie",
      "rank": "Barbie #019",
      "author": "Author 9",
      "price_eth": "3.9",
      "price_usd": "5000"
    },
    {
      "id": "5632",
      "image": "https://s.alicdn.com/@sc04/kf/H6dc1e764743e44e7aeca6cfc1ccd0d6aS.png_300x300.jpg",
      "title": "Car",
      "rank": "Car #230",
      "author": "Author 7",
      "price_eth": "8",
      "price_usd": "3000"
    }
  ]
}
